statemachine/__init__.py
statemachine/callbacks.py
statemachine/contrib/__init__.py
statemachine/contrib/diagram.py
statemachine/dispatcher.py
statemachine/engines/__init__.py
statemachine/engines/async_.py
statemachine/engines/sync.py
statemachine/event.py
statemachine/event_data.py
statemachine/events.py
statemachine/exceptions.py
statemachine/factory.py
statemachine/graph.py
statemachine/i18n.py
statemachine/locale/en/LC_MESSAGES/statemachine.po
statemachine/locale/pt_BR/LC_MESSAGES/statemachine.po
statemachine/mixins.py
statemachine/model.py
statemachine/py.typed
statemachine/registry.py
statemachine/signature.py
statemachine/state.py
statemachine/statemachine.py
statemachine/states.py
statemachine/transition.py
statemachine/transition_list.py
statemachine/utils.py
python_statemachine-2.3.5.dist-info/LICENSE
python_statemachine-2.3.5.dist-info/METADATA
python_statemachine-2.3.5.dist-info/WHEEL
python_statemachine-2.3.5.dist-info/RECORD
