Metadata-Version: 2.1
Name: python-statemachine
Version: 2.3.5
Summary: Python Finite State Machines made easy.
Home-page: https://github.com/fgmacedo/python-statemachine
License: MIT
Author: Fernando Macedo
Author-email: fgmacedo@gmail.com
Maintainer: Fernando Macedo
Maintainer-email: fgmacedo@gmail.com
Requires-Python: >=3.7
Classifier: Framework :: AsyncIO
Classifier: Intended Audience :: Developers
Classifier: License :: OSI Approved :: MIT License
Classifier: Natural Language :: English
Classifier: Programming Language :: Python :: 3
Classifier: Programming Language :: Python :: 3.7
Classifier: Programming Language :: Python :: 3.8
Classifier: Programming Language :: Python :: 3.9
Classifier: Programming Language :: Python :: 3.10
Classifier: Programming Language :: Python :: 3.11
Classifier: Programming Language :: Python :: 3.12
Classifier: Programming Language :: Python :: 3.13
Classifier: Topic :: Software Development :: Libraries
Provides-Extra: diagrams
